{
    "text": {
        "1": {
            "0": "שקורא אותה בברכה כצ\"ל (הגהות מאלפס ישן):"
        },
        "4": {
            "0": "נ\"ב כך הוא גי' הש\"ס למדתי שאין נכנסין לחורב' ולמדתי שמתפללין בדרך וכו':"
        },
        "6": {
            "0": "נ\"ב א\"ר לוי:",
            "1": "מעלה אני עליו:"
        },
        "7": {
            "0": "שיש בהתחל' הזמן כו' ושני זמנים בסוף הזמן וכו':",
            "1": "דאין סוף זמנה:",
            "2": "שסוף זמנה:",
            "3": "דסוף זמן ק\"ש לכתחלה אינו אלא עד הנץ כו' ותיבת סוף מוקפת:",
            "4": "ולפיכך היו:",
            "5": "נ\"ב שצ\"ל גבי תפלה ולכן רשמתי תיבת המנחה ודוק ותפלת המנחה לאו דוקא שה\"ה לתפלת שחרית כדמוכח בפרק תפלת השחר אמר רחב\"א וכו' מצוה להתפלל עם דמדומי חמה ואמר ר\"ז מאי קרא ייראוך עם שמש ולפני ירח דור דורי' לייטי עלה במערבא אמאן דמצלי עם דמדומי חמה מ\"ט דלמא מטרפא ליה שעתא ופירש\"י עם דמדומי חמה תפלת יוצר עם הנץ החמה ותפלת מנח' עם שקיעת החמה לייטי וכו' על מי שמשהה תפלת המנחה עם דמדומי חמה שמא תטרף ליה השעה ע\"י: אונס ויעבור הזמן עכ\"ל:",
            "6": "ויכול אחר הנץ לקרות ק\"ש ולסמוך אח\"כ גאולה כו':",
            "7": "וגומרה. כ\"ה בא\"י:"
        },
        "8": {
            "0": "נ\"ב אבר מן החי מן לא תאכל הנפש עם הבשר נפקא ובשר מן החי מבשר בשדה טרפה נפקא ולא מלא תאכלו על הדם דהוא לאו שבכללות:"
        },
        "9": {
            "0": "ואמונה וכן לקמן:",
            "1": "שאמרו כצ\"ל:",
            "2": "לאלתר וכן להלן בכל המקומות:"
        },
        "13": {
            "0": "בא\"י תז\"מ:",
            "1": "נ\"ב וכ\"מ מעובדא דר' חייא ורבי שהיו מעבירי' ידיהם על עיניהם כדי לכוין יותר או כדי שלא יראוהו סתום עינים:",
            "2": "ול' אמר רבא לא משמע דפליג וגם הטור נראה שאינו מפרש כן:"
        },
        "15": {
            "0": "נ\"ב בגמ' לא גריס זה:",
            "1": "אמיא בעידן ק\"ש ותי' וה\"מ נמחק:",
            "2": "נ\"ב אותו::"
        },
        "16": {
            "0": "נ\"ב היינו לשמואל:"
        },
        "18": {
            "0": "וגו':",
            "1": "בחמי:",
            "2": "דאנינות ליל. ותיבת של נמחק:"
        },
        "19": {
            "0": "תא\"מ ונ\"ב לפי דברי ר\"י אין נמצא כ\"ז בנוסחאות:",
            "1": "שיהא:",
            "2": "בתורה:",
            "3": "כיון כו' למצוה לא:",
            "4": "שנתחייב:"
        },
        "20": {
            "0": "נ\"ב להיתר:",
            "1": "נ\"ב אבל זה צ\"ע דהא הוא אונן ואין הלכה כדברי המיקל באונן:",
            "2": "ואע\"פ שאינו חייב:"
        },
        "21": {
            "0": "נ\"ב בגמ' יש עוד אפילו בשעה ששלום על ישראל יוליכם ה' את פועלי האון:"
        },
        "22": {
            "0": "נ\"ב וכו' חובתן אינו מוציא עד:",
            "1": "נ\"ב וההודעה:"
        },
        "24": {
            "0": "להביא ביחיד:",
            "1": "אפ\"ה נמחק ונ\"ב וגם אינו:",
            "2": "נ\"ב שלא לחדש:",
            "3": "נ\"ב בעי:",
            "4": "הרמב\"ם:"
        },
        "25": {
            "0": "נ\"ב על שאנו מודים לך:",
            "1": "נ\"ב בלבב שלם וכו':",
            "2": "לשמך הגדול:",
            "3": "נ\"ב לימא תנן סתמא כר\"א (פי' והלכה כמותו) דאמר עד הנץ החמה אפי' תימא ר' יהושע ודלמא כוותיקין:"
        },
        "26": {
            "0": "נ\"ב ודוקא בבה\"כ קבוע חיישינן שמא יפנה בהן אבל בבה\"כ ארעי שאין רגילות לפנות שם מותר להשתין בהם ולא חיישינן שמא יפנה בהם והא דתניא לקמן לא ישתין בהם אפי' בבה\"כ ארעי היינו דוקא כשאוחזן בידו דחיישינן שמא ישפשף בהם הניצוצות אם יפלו מים ברגליו או יגע באמה:",
            "1": "יכול וכו' שהוא צריך:",
            "2": "כדי לגמור את כולה:",
            "3": "ולא אמר דכ\"ע שהה כדי לגמור את כולה אינו חוזר לראש משמע:",
            "4": "נוגעות כצ\"ל:"
        },
        "28": {
            "0": "תא\"מ:"
        },
        "29": {
            "0": "הכנסת:",
            "1": "בידו כצ\"ל:"
        },
        "31": {
            "0": "ת\"ז מוקפת:",
            "1": "שמתוך כצ\"ל:",
            "2": "אין מרחיקין:",
            "3": "נ\"ב ושבת:"
        },
        "32": {
            "0": "כשמגלה כצ\"ל:",
            "1": "מוקצ' וחצר כצ\"ל ותי' הגנה נמחק:",
            "2": "נ\"ב כל עשרה כצ\"ל:"
        },
        "33": {
            "0": "שנים וכו':",
            "1": "שהן כו': ועם הכלי שאינן כליין כצ\"ל:",
            "2": "שהוא וכו' מאחר וכו' ועם הכלי שאינן כליין כצ\"ל:",
            "3": "בו כצ\"ל:"
        },
        "34": {
            "0": "נ\"ב הנרא':",
            "1": "נ\"ב שחרי':"
        },
        "36": {
            "0": "שיתבאר בירושלמי:",
            "1": "אבל כצ\"ל:"
        },
        "42": {
            "0": "היכא דאידגן כצ\"ל ותיבת דהיא נמחק:",
            "1": "בא\"י הגי' בכ\"מ תחנונים:"
        },
        "43": {
            "0": "צ\"ל התפלה:",
            "1": "צ\"ל תפלה:"
        },
        "47": {
            "0": "משום חד הכי אמר ר' אמי:"
        },
        "48": {
            "0": "חכם מאי עביד ליה הא עבד לי' איסורי' אלא אמר רבא ילך אצל חכם וכו' סדר ברכות:",
            "1": "מי סלקא:",
            "2": "שחרכן ואינו:"
        },
        "49": {
            "0": "עיי בב\"י סי' ר\"ב:",
            "1": "תא\"מ:",
            "2": "בכל וב\"ח מחק אותו:"
        },
        "51": {
            "0": "נ\"ב ר\"ל בין שהיה הקמח על גבי מים רותחין בין רותחין על גבי קמח:",
            "1": "ומקטפין:",
            "2": "נ\"ב דמשום ותיבת דמתוך מוקפת:"
        },
        "52": {
            "0": "נ\"ב והרי\"ף ותיבת הכי נמחק:"
        },
        "53": {
            "0": "תא\"מ:",
            "1": "גם תא\"מ וצ\"ל כרבא:"
        },
        "54": {
            "0": "ושלימה משנתך:",
            "1": "אין צריך לחזור והשאר נמחק:",
            "2": "נ\"ב וכו':",
            "3": "תורם מהשלימה כו' ור\"י דאמר חצי בצל גדול כו':"
        },
        "55": {
            "0": "נ\"ב מלח:",
            "1": "נ\"ב שברכה אחת ותי' כולה נמחק:"
        },
        "57": {
            "0": "כיון שחייב באכילתו:",
            "1": "תא\"מ:",
            "2": "תז\"מ:"
        },
        "58": {
            "0": "אייתי לקמייהו מידי למיכל:",
            "1": "תז\"מ:",
            "2": "משמע כצ\"ל:",
            "3": "לאכול ולא:"
        },
        "59": {
            "0": "לאכול:",
            "1": "בברכת המוציא:"
        },
        "61": {
            "0": "תי' אותו נמחק:"
        },
        "62": {
            "0": "ועל היין:"
        },
        "65": {
            "0": "מן שאכלו עד בהמ\"ז מוקפות:",
            "1": "סברוה כצ\"ל ותי' מאי לאו נמחק:",
            "2": "מאי לאו בהא:",
            "3": "תי' וכן נמחק:"
        },
        "66": {
            "0": "תז\"מ:",
            "1": "הזימון כצ\"ל:"
        },
        "67": {
            "0": "ושיזכיר הטוב ומטיב אח\"כ מלבד מה שאומר בכל יום שאם נפרש שהטוב והמטיב שאומר בכל יום שאומר הוא דאומר ת\"ק מה חדוש כצ\"ל:",
            "1": "לחבירו להמתינו כצ\"ל:",
            "2": "נ\"ב ר\"ל האריך:",
            "3": "צ\"ל ר' אבא:",
            "4": "מה פליגי מה כצ\"ל:",
            "5": "נ\"ב מה:",
            "6": "כוסו כצ\"ל:"
        },
        "68": {
            "0": "נ\"ב כיון:",
            "1": "ת\"ז נמחק:",
            "2": "או שלא הביאו שתי שערות:",
            "3": "תז\"מ:"
        },
        "69": {
            "0": "ומלכות בית דוד בבונה ירושלים:"
        },
        "70": {
            "0": "אין זה ענין כצ\"ל:"
        },
        "71": {
            "0": "תז\"מ:",
            "1": "תז\"מ:",
            "2": "תז\"מ:",
            "3": "נ\"ב והדר מקשי בשאלה נמי הא כתיב הרחב פיך ואמלאהו ההוא בד\"ת כתיב:"
        },
        "72": {
            "0": "שר\"ל כצ\"ל:",
            "1": "אינו:",
            "2": "אלא הכא מיירי שבאו מג' חבורות של ג' ג' בני אדם:",
            "3": "תז\"מ:",
            "4": "כאחת:",
            "5": "כיון שכבר כצ\"ל ותי' אע\"פ נמחק:"
        },
        "73": {
            "0": "תא\"מ:"
        },
        "74": {
            "0": "בלבד:"
        },
        "75": {
            "0": "אומרה על היין:"
        },
        "76": {
            "0": "יברך כצ\"ל וכן לקמן וכן בתר\"י:",
            "1": "מתניתא כצ\"ל וכן לקמן:",
            "2": "לחול:",
            "3": "על מה שרוצה לשתות:",
            "4": "מש\"ה גזרו:",
            "5": "נ\"ב כ\"ז שייך לקמן גבי היה מהלך חוץ לכרך והריח ריח טוב:"
        },
        "78": {
            "0": "מפטר נפשייהו:",
            "1": "באור שיצא מן העצים ומן האבנים כצ\"ל:",
            "2": "תז\"מ:"
        },
        "80": {
            "0": "ולטבילת כצ\"ל:",
            "1": "תז\"מ:",
            "2": "למדנו:"
        },
        "81": {
            "0": "תז\"מ:",
            "1": "על:",
            "2": "נ\"ב ר\"ל:",
            "3": "תז\"מ:"
        },
        "85": {
            "0": "וכן כשיחזרו כל כוכב וכוכב מחמשת הכוכבים הנשארים לתחלת מזל טלה ולא תהיה נוטה לא לצפון ולא לדרום:",
            "1": "מקצה המזרח כצ\"ל:"
        },
        "86": {
            "0": "תוליכני:",
            "1": "אם יסתם:",
            "2": "היא ליתא:",
            "3": "כל המעשים אדון:",
            "4": "להבין:"
        },
        "87": {
            "0": "שעשה:",
            "1": "בדרך:",
            "2": "השלימה שאדם ונראה כי מן השלימה נשתבש והיה שלו מה:"
        },
        "88": {
            "0": "נ\"ב לב\"ה ע\"מ:",
            "1": "בש\"ס גריס מותר:",
            "2": "אם יש לו מקום המיוחד לו ותיבת ואפי' נמחק:",
            "3": "סליק פרקא וסליקו להו חידושי מסכת ברכות על הדרך שקבל אותם אחד מתלמידי הרב רבינו יונה ז\"ל נר\"ו הרחמן הוא יזכנו ללמוד וללמד ולשמור ולעשות אמן:"
        }
    },
    "meta": "Daf-Comment",
    "work": "Hagahot MeAlfas Yashan on Berakhot"
}