{
    "depth": 2, 
    "base_text_titles": [
        {
            "en": "Bava Batra", 
            "he": "בבא בתרא"
        }
    ], 
    "heCategories": [
        "תלמוד", 
        "בבלי", 
        "מפרשים", 
        "חכמת שלמה", 
        "סדר נזיקין"
    ], 
    "title": "Chokhmat Shlomo on Bava Batra", 
    "collective_title": {
        "en": "Chokhmat Shlomo", 
        "he": "חכמת שלמה"
    }, 
    "heTitleVariants": [
        "מהרש\"ל בבא בתרא", 
        "חכמת שלמה על בבא בתרא"
    ], 
    "dependence": "Commentary", 
    "heTitle": "חכמת שלמה על בבא בתרא", 
    "authors": [
        {
            "en": "Maharshal", 
            "he": "מהרש\"ל"
        }
    ], 
    "titleVariants": [
        "Maharshal on Bava Batra", 
        "Chokhmat Shlomo on Bava Batra"
    ], 
    "sectionNames": [
        "Daf", 
        "Comment"
    ], 
    "categories": [
        "Talmud", 
        "Bavli", 
        "Commentary", 
        "Chokhmat Shlomo", 
        "Seder Nezikin"
    ], 
    "schema": {
        "nodeType": "JaggedArrayNode", 
        "title": "Chokhmat Shlomo on Bava Batra", 
        "addressTypes": [
            "Talmud", 
            "Integer"
        ], 
        "heTitle": "חכמת שלמה על בבא בתרא", 
        "depth": 2, 
        "titles": [
            {
                "lang": "en", 
                "text": "Maharshal on Bava Batra"
            }, 
            {
                "lang": "he", 
                "text": "מהרש\"ל בבא בתרא"
            }, 
            {
                "lang": "he", 
                "text": "חכמת שלמה על בבא בתרא", 
                "primary": true
            }, 
            {
                "lang": "en", 
                "text": "Chokhmat Shlomo on Bava Batra", 
                "primary": true
            }
        ], 
        "key": "Chokhmat Shlomo on Bava Batra", 
        "heSectionNames": [
            "דף", 
            "פירוש"
        ], 
        "sectionNames": [
            "Daf", 
            "Comment"
        ]
    }
}