{
    "title": "Hagahot She'erit Tzion",
    "categories": [
        "Reference",
        "Encyclopedic Works",
        "Shem HaGedolim"
    ],
    "schema": {
        "nodeType": "JaggedArrayNode",
        "depth": 2,
        "addressTypes": [
            "Seif",
            "Section"
        ],
        "sectionNames": [
            "Seif",
            "Paragraph"
        ],
        "titles": [
            {
                "text": "Hagahot Sheerit Tzion",
                "lang": "en"
            },
            {
                "text": "הגהות שארית ציון",
                "lang": "he",
                "primary": true
            },
            {
                "text": "Hagahot She'erit Tzion",
                "lang": "en",
                "primary": true
            }
        ],
        "title": "Hagahot She'erit Tzion",
        "heTitle": "הגהות שארית ציון",
        "heSectionNames": [
            "סעיף",
            "פסקה"
        ],
        "key": "Hagahot She'erit Tzion"
    },
    "authors": [
        {
            "en": "Menachem Mendel Krengel",
            "he": "מנחם מאנדל קרנגל",
            "slug": "menachem-mendel-krengel"
        }
    ],
    "enDesc": "She’erit Tzion is a compilation of Rabbi Menachem Mendel Krengel’s footnotes to Rabbi Chaim Yosef David Azulai’s Shem HaGedolim, included in the revised edition of Shem HaGedolim published by Krengel. Krengel also published a first set of footnotes under the title Menachem Tzion.",
    "heDesc": "\"שארית ציון\" הוא חיבור של הערות שוליים מורחב על ספרו של הרב חיים יוסף דוד אזולאי (החיד\"א) - \"שם הגדולים\" - חיבור ביוגרפי־ביבליוגרפי על חכמי ישראל וחיבורים תורניים מהמאה ה-18. ההערות נכתבו במאה ה-19 על ידי הרב מנחם מאנדל קרנגל - בקרקוב, פולין. הערות השוליים כוללות פירושים, הפניות למקורות בהם השתמש החיד\"א, ואף קטעים שהושמטו במהדורות קודמות של \"שם הגדולים\". המחבר כתב גם הערות שוליים מתומצטות יותר  ל\"שם הגדולים\" בספרו \"מנחם ציון\".",
    "enShortDesc": "Rabbi Menachem Mendel Krengel’s additions to his Hagahot Menachem Tzion.",
    "heShortDesc": "\"שארית ציון\" הוא חיבור מהמאה ה-19 שנכתב על ידי הרב מנחם מאנדל קרנגל, המכיל הערות שוליים מורחבות על ספר \"שם הגדולים\" של החיד\"א מהמאה ה-18.",
    "pubDate": "1930",
    "compDate": "1904",
    "compPlace": "Krakow, Poland",
    "pubPlace": "Piotrków Trybunalski",
    "errorMargin": "3",
    "era": "AH",
    "dependence": "Commentary",
    "base_text_titles": [
        {
            "en": "Shem HaGedolim, Maarekhet Sefarim",
            "he": "שם הגדולים, מערכת ספרים"
        },
        {
            "en": "Kuntres Peleitat Sefarim",
            "he": "קונטרס פליטת ספרים"
        }
    ],
    "heTitle": "הגהות שארית ציון",
    "titleVariants": [
        "Hagahot Sheerit Tzion",
        "Hagahot She'erit Tzion"
    ],
    "heTitleVariants": [
        "הגהות שארית ציון"
    ],
    "sectionNames": [
        "Seif",
        "Paragraph"
    ],
    "depth": 2,
    "heCategories": [
        "מילונים וספרי יעץ",
        "אנציקלופדיות",
        "שם הגדולים"
    ],
    "compDateString": {
        "en": " (c.1901  - c.1907 CE)",
        "he": " (1901 - 1907 לספירה בקירוב)"
    },
    "compPlaceString": {
        "en": "Krakow, Poland",
        "he": "קרקוב, פולין"
    }
}