{
    "is_cited": true, 
    "sectionNames": [
        "Daf", 
        "Halakhah"
    ], 
    "heCategories": [
        "תלמוד", 
        "ירושלמי", 
        "סדר זרעים"
    ], 
    "pubDate": "1523", 
    "title": "Jerusalem Talmud Hallah", 
    "compDate": "400", 
    "pubPlace": "Venice", 
    "compPlace": "Talmudic Israel", 
    "enDesc": "Hallah (Glob of Dough) belongs to the first order, Zera'im (seeds) and discusses the laws regarding the hallah offering of dough to be given to the Kohanim, as stated in Numbers 15:18-21. It consists of four chapters.", 
    "depth": 2, 
    "heTitleVariants": [
        "תלמוד ירושלמי חלה", 
        "ירושלמי חלה"
    ], 
    "compPlaceString": {
        "en": "Talmudic Israel", 
        "he": "ישראל התלמודית"
    }, 
    "compDateString": {
        "en": " (c.375  - c.425 CE)", 
        "he": " (375 - 425 לספירה בקירוב)"
    }, 
    "heTitle": "תלמוד ירושלמי חלה", 
    "era": "A", 
    "authors": [], 
    "titleVariants": [
        "Yerushalmi Hallah", 
        "Talmud Yerushalmi Challah", 
        "JT Hallah", 
        "Yerushalmi Challah", 
        "JT Challah", 
        "Jerusalem Talmud Challah", 
        "Jerusalem Talmud Hallah"
    ], 
    "errorMargin": "25", 
    "order": [
        9
    ], 
    "categories": [
        "Talmud", 
        "Yerushalmi", 
        "Seder Zeraim"
    ], 
    "schema": {
        "nodeType": "JaggedArrayNode", 
        "addressTypes": [
            "Talmud", 
            "Integer"
        ], 
        "lengths": [
            56, 
            87
        ], 
        "title": "Jerusalem Talmud Hallah", 
        "heTitle": "תלמוד ירושלמי חלה", 
        "depth": 2, 
        "titles": [
            {
                "lang": "en", 
                "text": "Yerushalmi Hallah"
            }, 
            {
                "lang": "en", 
                "text": "Talmud Yerushalmi Challah"
            }, 
            {
                "lang": "en", 
                "text": "JT Hallah"
            }, 
            {
                "lang": "en", 
                "text": "Yerushalmi Challah"
            }, 
            {
                "lang": "en", 
                "text": "JT Challah"
            }, 
            {
                "lang": "en", 
                "text": "Jerusalem Talmud Challah"
            }, 
            {
                "lang": "he", 
                "text": "תלמוד ירושלמי חלה", 
                "primary": true
            }, 
            {
                "lang": "he", 
                "text": "ירושלמי חלה"
            }, 
            {
                "lang": "en", 
                "text": "Jerusalem Talmud Hallah", 
                "primary": true
            }
        ], 
        "key": "Jerusalem Talmud Hallah", 
        "heSectionNames": [
            "דף", 
            "הלכה"
        ], 
        "sectionNames": [
            "Daf", 
            "Halakhah"
        ]
    }
}