{
    "versionTitle": "Rabbi David Etengoff", 
    "language": "en", 
    "title": "Sefer HaMitzvot", 
    "text": {
        "Shorashim": [], 
        "Negative Commandments": [], 
        "Positive Commandments": [
            [], 
            [], 
            [], 
            [], 
            [], 
            [], 
            [], 
            [], 
            [], 
            [], 
            [], 
            [], 
            [], 
            [], 
            [], 
            [], 
            [], 
            [], 
            [], 
            [], 
            [], 
            [], 
            [], 
            [], 
            [], 
            [], 
            [], 
            [], 
            [], 
            [], 
            [], 
            [], 
            [], 
            [], 
            [], 
            [], 
            [], 
            [], 
            [], 
            [], 
            [], 
            [], 
            [], 
            [], 
            [], 
            [], 
            [], 
            [], 
            [], 
            [], 
            [], 
            [], 
            [], 
            [], 
            [], 
            [], 
            [], 
            [], 
            [], 
            [], 
            [], 
            [], 
            [], 
            [], 
            [], 
            [], 
            [], 
            [], 
            [], 
            [], 
            [], 
            [], 
            [], 
            [], 
            [], 
            [], 
            [], 
            [], 
            [], 
            [], 
            [], 
            [], 
            [], 
            [], 
            [], 
            [], 
            [], 
            [], 
            [], 
            [], 
            [], 
            [], 
            [], 
            [], 
            [], 
            [], 
            [], 
            [], 
            [], 
            [], 
            [], 
            [], 
            [], 
            [], 
            [], 
            [], 
            [], 
            [], 
            [], 
            [], 
            [], 
            [], 
            [], 
            [], 
            [], 
            [], 
            [], 
            [], 
            [], 
            [], 
            [], 
            [], 
            [], 
            [], 
            [], 
            [], 
            [], 
            [], 
            [], 
            [], 
            [], 
            [], 
            [], 
            [], 
            [], 
            [], 
            [], 
            [], 
            [], 
            [], 
            [], 
            [], 
            [], 
            [], 
            [], 
            [], 
            [], 
            [], 
            [], 
            [], 
            [], 
            [], 
            [], 
            [], 
            [], 
            [], 
            [], 
            [], 
            [], 
            [], 
            [], 
            [], 
            [], 
            [], 
            [], 
            [], 
            [], 
            [], 
            [], 
            [], 
            [], 
            [], 
            [], 
            [], 
            [], 
            [], 
            [], 
            [], 
            [], 
            [], 
            [], 
            [], 
            [], 
            [], 
            [], 
            [], 
            [], 
            [], 
            [], 
            [], 
            [], 
            [], 
            [], 
            [], 
            [], 
            [], 
            [], 
            [], 
            [], 
            [], 
            [], 
            [], 
            [], 
            [], 
            [], 
            [
                "My mercy and love for my brother [my fellow Jew] should be exactly like the mercy and love I have for myself; [specifically in regards to] his money, physical welfare, and everything that will ever be in his possession or he will want. And, everything that I wish for myself, I should desire for him. [Conversely,] anything that I would hate for myself or for anyone who associates with me, I should find hateful to him in the exact same fashion. This is what the Torah stated: “… and you shall love your neighbor as yourself"
            ]
        ], 
        "Introductions": {
            "The Rambam's Introduction": [], 
            "Translator's Introduction": []
        }, 
        "Conclusion for Positive Commandments": [], 
        "Introduction to the counting of the Mitzvot": []
    }, 
    "versionSource": "http://www.thejewishstar.com/stories/what-is-halachic-love,13500", 
    "heTitle": "ספר המצוות", 
    "categories": [
        "Halakhah"
    ], 
    "schema": {
        "heTitle": "ספר המצוות", 
        "nodes": [
            {
                "heTitle": "הקדמות", 
                "nodes": [
                    {
                        "heTitle": "הקדמת המתרגם", 
                        "enTitle": "Translator's Introduction"
                    }, 
                    {
                        "heTitle": "הקדמת הרמב\"ם", 
                        "enTitle": "The Rambam's Introduction"
                    }
                ], 
                "enTitle": "Introductions"
            }, 
            {
                "heTitle": "שורשים", 
                "enTitle": "Shorashim"
            }, 
            {
                "heTitle": "הקדמה למניין המצוות", 
                "enTitle": "Introduction to the counting of the Mitzvot"
            }, 
            {
                "heTitle": "מצוות עשה", 
                "enTitle": "Positive Commandments"
            }, 
            {
                "heTitle": "סיום מצוות עשה", 
                "enTitle": "Conclusion for Positive Commandments"
            }, 
            {
                "heTitle": "מצוות לא תעשה", 
                "enTitle": "Negative Commandments"
            }
        ], 
        "key": "Sefer HaMitzvot", 
        "enTitle": "Sefer HaMitzvot"
    }
}